am4894plots/__init__.py
am4894plots/am4894plots.py
am4894plots/plots.py
am4894plots/utils.py
am4894plots/dists/__init__.py
am4894plots/dists/bokeh.py
am4894plots/dists/plotly.py
am4894plots/heatmap/__init__.py
am4894plots/heatmap/plotly.py
am4894plots/lines/__init__.py
am4894plots/lines/bokeh.py
am4894plots/lines/plotly.py
am4894plots/scatters/__init__.py
am4894plots/scatters/plotly.py
am4894plots-0.2.0.dist-info/AUTHORS.rst
am4894plots-0.2.0.dist-info/LICENSE
am4894plots-0.2.0.dist-info/METADATA
am4894plots-0.2.0.dist-info/WHEEL
am4894plots-0.2.0.dist-info/top_level.txt
am4894plots-0.2.0.dist-info/RECORD
